retinalysis_enface-0.0.3.dist-info/licenses/LICENSE
rtnls_enface/__init__.py
rtnls_enface/base.py
rtnls_enface/disc.py
rtnls_enface/faz.py
rtnls_enface/faz_enface.py
rtnls_enface/fundus.py
rtnls_enface/loader.py
rtnls_enface/grids/__init__.py
rtnls_enface/grids/base.py
rtnls_enface/grids/etdrs.py
rtnls_enface/qc/__init__.py
rtnls_enface/qc/validators.py
rtnls_enface/utils/__init__.py
rtnls_enface/utils/data_loading.py
rtnls_enface/utils/image.py
rtnls_enface/utils/plotting.py
retinalysis_enface-0.0.3.dist-info/METADATA
retinalysis_enface-0.0.3.dist-info/WHEEL
retinalysis_enface-0.0.3.dist-info/top_level.txt
retinalysis_enface-0.0.3.dist-info/RECORD
