Metadata-Version: 2.4
Name: retinalysis-enface
Version: 0.0.3
Summary: Utilities for analyzing retinal enface images
Author-email: Jose Vargas <j.vargasquiros@erasmusmc.nl>
License:                     GNU AFFERO GENERAL PUBLIC LICENSE
Project-URL: Homepage, https://github.com/Eyened/retinalysis-enface
Project-URL: Bug Tracker, https://github.com/Eyened/retinalysis-enface/issues
Requires-Python: <3.12,>=3.10
License-File: LICENSE
Requires-Dist: numpy==2.*
Requires-Dist: pandas==2.*
Requires-Dist: scikit-learn==1.*
Requires-Dist: scipy==1.*
Requires-Dist: opencv-python==4.*
Requires-Dist: matplotlib==3.*
Requires-Dist: joblib==1.*
Requires-Dist: tqdm==4.*
Requires-Dist: Pillow==11.*
Requires-Dist: click==8.*
Requires-Dist: pydicom==3.*
Requires-Dist: scikit-image==0.24.0
Dynamic: license-file
